pyenvcomp/__init__.py
pyenvcomp/main.py
pyenvcomp-1.0.3.dist-info/METADATA
pyenvcomp-1.0.3.dist-info/WHEEL
pyenvcomp-1.0.3.dist-info/entry_points.txt
pyenvcomp-1.0.3.dist-info/top_level.txt
pyenvcomp-1.0.3.dist-info/RECORD
