Metadata-Version: 2.1
Name: pyenvcomp
Version: 1.0.3
Summary: Detailed display of the difference between two given python virtual environments.
Home-page: https://github.com/KoustavCode/pyenvcomp.git
Author: Koustav Chanda
Author-email: koustavtocode@gmail.com
License: MIT
Platform: UNKNOWN
Classifier: License :: OSI Approved :: MIT License
Classifier: Programming Language :: Python :: 3
Classifier: Programming Language :: Python :: 3.8
Requires-Dist: colorama
Requires-Dist: colored
Requires-Dist: tableformatter
